thesleepinglion/__init__.py
thesleepinglion/aliases.py
thesleepinglion/backupFileHandler.py
thesleepinglion/card.py
thesleepinglion/commands.py
thesleepinglion/constants.py
thesleepinglion/errors.py
thesleepinglion/gloomhavenclass.py
thesleepinglion/gloomhavenlexer.py
thesleepinglion/gloomhavenparser.py
thesleepinglion/gmllinecontext.py
thesleepinglion/hexagonal_grid.py
thesleepinglion/items.py
thesleepinglion/macros.py
thesleepinglion/main.py
thesleepinglion/svg_wrapper.py
thesleepinglion/utils.py
thesleepinglion/assets/__init__.py
thesleepinglion/assets/add_target.svg
thesleepinglion/assets/any_element.svg
thesleepinglion/assets/attack.svg
thesleepinglion/assets/bless.svg
thesleepinglion/assets/consume.svg
thesleepinglion/assets/curse.svg
thesleepinglion/assets/dark.svg
thesleepinglion/assets/definitive_loss.svg
thesleepinglion/assets/disarm.svg
thesleepinglion/assets/earth.svg
thesleepinglion/assets/enhancement_dot.svg
thesleepinglion/assets/experience.svg
thesleepinglion/assets/fire.svg
thesleepinglion/assets/fly.svg
thesleepinglion/assets/heal.svg
thesleepinglion/assets/ice.svg
thesleepinglion/assets/immobilize.svg
thesleepinglion/assets/infinity.svg
thesleepinglion/assets/invisible.svg
thesleepinglion/assets/jump.svg
thesleepinglion/assets/light.svg
thesleepinglion/assets/loot.svg
thesleepinglion/assets/loss.svg
thesleepinglion/assets/move.svg
thesleepinglion/assets/muddle.svg
thesleepinglion/assets/not_found.svg
thesleepinglion/assets/one_charge.svg
thesleepinglion/assets/pierce.svg
thesleepinglion/assets/poison.svg
thesleepinglion/assets/pull.svg
thesleepinglion/assets/push.svg
thesleepinglion/assets/range.svg
thesleepinglion/assets/recover_card.svg
thesleepinglion/assets/retaliate.svg
thesleepinglion/assets/round_bonus.svg
thesleepinglion/assets/shield.svg
thesleepinglion/assets/strengthen.svg
thesleepinglion/assets/stun.svg
thesleepinglion/assets/summon_1_block.png
thesleepinglion/assets/summon_2_blocks.png
thesleepinglion/assets/target.svg
thesleepinglion-1.2.0.dist-info/LICENSE
thesleepinglion-1.2.0.dist-info/METADATA
thesleepinglion-1.2.0.dist-info/WHEEL
thesleepinglion-1.2.0.dist-info/entry_points.txt
thesleepinglion-1.2.0.dist-info/top_level.txt
thesleepinglion-1.2.0.dist-info/RECORD
