Metadata-Version: 2.1
Name: thesleepinglion
Version: 1.2.0
Summary: Automatic card layout creation for Gloomhaven custom classes
Author: Guillaume Vigne
License: MIT
License-File: LICENSE
Requires-Dist: numpy
Requires-Dist: PyGObject
Requires-Dist: pyyaml
Requires-Dist: cairosvg
Requires-Dist: regex
Requires-Dist: manimpango
